[
{
"id": 1,
"caption": "สิ่งที่ผมได้เรียนรู้จากประสบการณ์จริง"
},
{
"id": 2,
"caption": "ผมเคยคิดผิดเกี่ยวกับเรื่องนี้มาตลอด"
},
{
"id": 3,
"caption": "ถ้าย้อนเวลากลับไปได้ นี่คือสิ่งที่ผมจะบอกตัวเอง"
},
{
"id": 4,
"caption": "บทเรียนสำคัญที่ไม่มีใครสอนในห้องเรียน"
},
{
"id": 5,
"caption": "สิ่งที่เปลี่ยนวิธีคิดของผมไปตลอดกาล"
},
{
"id": 6,
"caption": "นี่คือมุมมองส่วนตัวของผมต่อเรื่องนี้"
},
{
"id": 7,
"caption": "จากประสบการณ์ที่ผ่านมา ผมค้นพบว่า..."
},
{
"id": 8,
"caption": "บางครั้งความล้มเหลวก็สอนเราได้มากกว่าความสำเร็จ"
},
{
"id": 9,
"caption": "สิ่งที่ผมอยากแบ่งปันให้คนที่กำลังเริ่มต้น"
},
{
"id": 10,
"caption": "ผมไม่ได้เก่งที่สุด แต่ผมอยากเล่าประสบการณ์นี้"
},
{
"id": 11,
"caption": "หนึ่งในบทเรียนที่คุ้มค่าที่สุดในชีวิตของผม"
},
{
"id": 12,
"caption": "ผมใช้เวลาหลายปีกว่าจะเข้าใจเรื่องนี้"
},
{
"id": 13,
"caption": "สิ่งที่ผมทำต่างจากเมื่อก่อน และผลลัพธ์ที่ได้"
},
{
"id": 14,
"caption": "นี่คือแนวคิดที่ช่วยให้ผมพัฒนาตัวเอง"
},
{
"id": 15,
"caption": "ผมเชื่อว่าความสำเร็จไม่ได้มีสูตรสำเร็จเดียว"
},
{
"id": 16,
"caption": "ประสบการณ์ครั้งนี้ทำให้ผมมองโลกต่างออกไป"
},
{
"id": 17,
"caption": "สิ่งที่ผมอยากให้ทุกคนรู้ก่อนเริ่มต้น"
},
{
"id": 18,
"caption": "นี่คือข้อผิดพลาดที่ผมไม่อยากให้คุณทำซ้ำ"
},
{
"id": 19,
"caption": "ถ้ามีคนถามผมเรื่องนี้ นี่คือคำตอบของผม"
},
{
"id": 20,
"caption": "ผมยังเรียนรู้อยู่ทุกวัน และนี่คือสิ่งที่ค้นพบล่าสุด"
}
]